tdpt/__init__.py
tdpt/__main__.py
tdpt/helpers.py
tdpt/backends/__init__.py
tdpt/backends/deluge.py
tdpt/backends/rtorrent.py
tdpt/backends/transmission.py
tdpt/handlers/__init__.py
tdpt/handlers/message_handlers.py
tests/__init__.py
tests/test_helpers.py
tdpt-1.3.dist-info/LICENSE
tdpt-1.3.dist-info/METADATA
tdpt-1.3.dist-info/WHEEL
tdpt-1.3.dist-info/entry_points.txt
tdpt-1.3.dist-info/top_level.txt
tdpt-1.3.dist-info/RECORD
