Metadata-Version: 2.1
Name: tdpt
Version: 1.3
Summary: Torrent downloading progress on Telegram
Home-page: https://github.com/dolohow/tdpt
Author: dolohow
Author-email: lukasz@zarnowiecki.pl
License: UNKNOWN
Keywords: telegram bot transmission liveupdates torrents rtorrent torrent
Platform: UNKNOWN
Classifier: Programming Language :: Python :: 3
Classifier: License :: OSI Approved :: GNU General Public License v3 (GPLv3)
Classifier: Operating System :: OS Independent
Requires-Python: >=3.6
Requires-Dist: python-telegram-bot (==13.1)
Requires-Dist: transmissionrpc (==0.11)
